plone.app.standardtiles-3.2.2-py3.13-nspkg.pth
plone/app/standardtiles/__init__.py
plone/app/standardtiles/attachment.py
plone/app/standardtiles/common.py
plone/app/standardtiles/configure.zcml
plone/app/standardtiles/content.zcml
plone/app/standardtiles/contentlisting.py
plone/app/standardtiles/discussion.py
plone/app/standardtiles/embed.py
plone/app/standardtiles/existingcontent.py
plone/app/standardtiles/field.py
plone/app/standardtiles/head.py
plone/app/standardtiles/head.zcml
plone/app/standardtiles/html.py
plone/app/standardtiles/interfaces.py
plone/app/standardtiles/layout.zcml
plone/app/standardtiles/linkintegrity.py
plone/app/standardtiles/media.zcml
plone/app/standardtiles/metadata.py
plone/app/standardtiles/navigation.py
plone/app/standardtiles/rawembed.py
plone/app/standardtiles/rss.py
plone/app/standardtiles/setuphandlers.py
plone/app/standardtiles/sitemap.py
plone/app/standardtiles/testing.py
plone/app/standardtiles/testing.zcml
plone/app/standardtiles/upgrades.py
plone/app/standardtiles/upgrades.zcml
plone/app/standardtiles/utils.py
plone/app/standardtiles/viewletmanager.py
plone/app/standardtiles/portlets/__init__.py
plone/app/standardtiles/portlets/add.py
plone/app/standardtiles/portlets/assignment.py
plone/app/standardtiles/portlets/configure.zcml
plone/app/standardtiles/portlets/delete.py
plone/app/standardtiles/portlets/edit.py
plone/app/standardtiles/portlets/portlet.py
plone/app/standardtiles/portlets/portletmanager.py
plone/app/standardtiles/portlets/utils.py
plone/app/standardtiles/portlets/vocabularies.py
plone/app/standardtiles/profiles/default/metadata.xml
plone/app/standardtiles/profiles/default/portlets.xml
plone/app/standardtiles/profiles/default/registry.xml
plone/app/standardtiles/profiles/uninstall/portlets.xml
plone/app/standardtiles/profiles/uninstall/registry.xml
plone/app/standardtiles/templates/attachment_listing.pt
plone/app/standardtiles/templates/configlets.pt
plone/app/standardtiles/templates/contentlisting_view.pt
plone.app.standardtiles-3.2.2.dist-info/LICENSE.GPL
plone.app.standardtiles-3.2.2.dist-info/LICENSE.txt
plone.app.standardtiles-3.2.2.dist-info/METADATA
plone.app.standardtiles-3.2.2.dist-info/WHEEL
plone.app.standardtiles-3.2.2.dist-info/entry_points.txt
plone.app.standardtiles-3.2.2.dist-info/namespace_packages.txt
plone.app.standardtiles-3.2.2.dist-info/top_level.txt
plone.app.standardtiles-3.2.2.dist-info/RECORD
