Metadata-Version: 2.2
Name: plone.app.standardtiles
Version: 3.2.2
Summary: Tiles for plone.app.blocks page composition
Home-page: https://github.com/plone/plone.app.standardtiles
Author: Rob Gietema
Author-email: rob@fourdigits.nl
License: GPL
Keywords: tiles content plone
Classifier: Development Status :: 5 - Production/Stable
Classifier: Environment :: Web Environment
Classifier: Framework :: Plone
Classifier: Framework :: Plone :: Addon
Classifier: Framework :: Plone :: 6.0
Classifier: License :: OSI Approved :: GNU General Public License v2 (GPLv2)
Classifier: Programming Language :: Python
Classifier: Programming Language :: Python :: 3.8
Classifier: Programming Language :: Python :: 3.9
Classifier: Programming Language :: Python :: 3.10
Classifier: Programming Language :: Python :: 3.11
Classifier: Topic :: Internet :: WWW/HTTP
Classifier: Topic :: Internet :: WWW/HTTP :: Dynamic Content
Classifier: Topic :: Software Development :: Libraries :: Python Modules
Requires-Python: >=3.8
License-File: LICENSE.GPL
License-File: LICENSE.txt
Requires-Dist: plone.api>=2.3.0
Requires-Dist: plone.app.blocks
Requires-Dist: plone.app.tiles>=4.0.0
Requires-Dist: plone.base
Requires-Dist: plone.subrequest
Requires-Dist: plone.tiles>=1.8.0
Requires-Dist: requests
Requires-Dist: setuptools
Requires-Dist: Zope
Provides-Extra: test
Requires-Dist: plone.app.testing; extra == "test"
Requires-Dist: plone.app.dexterity; extra == "test"
Requires-Dist: plone.app.discussion; extra == "test"
Requires-Dist: lxml; extra == "test"
Provides-Extra: attachment
Requires-Dist: plone.formwidget.multifile>=2.0; extra == "attachment"
Dynamic: author
Dynamic: author-email
Dynamic: classifier
Dynamic: description
Dynamic: home-page
Dynamic: keywords
Dynamic: license
Dynamic: provides-extra
Dynamic: requires-dist
Dynamic: requires-python
Dynamic: summary
